data/__init__.py
data/prepare_train_data.py
data/cityscapes/__init__.py
data/cityscapes/cityscapes_loader.py
data/kitti/__init__.py
data/kitti/kitti_odom_loader.py
data/kitti/kitti_raw_loader.py
kitti_eval/__init__.py
kitti_eval/depth_evaluation_utils.py
kitti_eval/eval_depth.py
kitti_eval/eval_pose.py
kitti_eval/pose_evaluation_utils.py
SfMLearner_installable-1.0.1.dist-info/LICENSE
SfMLearner_installable-1.0.1.dist-info/METADATA
SfMLearner_installable-1.0.1.dist-info/WHEEL
SfMLearner_installable-1.0.1.dist-info/top_level.txt
SfMLearner_installable-1.0.1.dist-info/RECORD
