Metadata-Version: 2.1
Name: SfMLearner-installable
Version: 1.0.1
Summary: Fork of the original SfMLearner with a setup.py file for installation with pip.
Home-page: https://github.com/topher097/SfMLearner_installable
Author: Christopher Endres
Author-email: cmendres400@gmail.com
License: MIT
Classifier: License :: OSI Approved :: MIT License
Classifier: Programming Language :: Python
Classifier: Programming Language :: Python :: 3
Classifier: Programming Language :: Python :: 3.6
Classifier: Programming Language :: Python :: Implementation :: CPython
Classifier: Programming Language :: Python :: Implementation :: PyPy
Requires-Python: >=3.6.0
License-File: LICENSE
Requires-Dist: joblib (>=1.2.0)
Requires-Dist: matplotlib (>=3.7.1)
Requires-Dist: numpy
Requires-Dist: Pillow (>=9.5.0)
Requires-Dist: scipy (>=1.10.1)
Requires-Dist: setuptools (>=65.5.0)
Requires-Dist: tensorflow (>=1.12.0)
